[
  {
    "id": "ahri",
    "name": "Ahri",
    "thumbnail": "https://ddragon.leagueoflegends.com/cdn/16.8.1/img/champion/Ahri.png",
    "factionKey": "ionia",
    "type": "champion",
    "canon": true,
    "version": "16.8.1",
    "related_characters": [
      {
        "id": "monkeyking",
        "type": "champion",
        "relation": "friend",
        "auto_generated": false,
        "note_fr": "Ami Vastaya",
        "note_en": "Vastaya friend"
      },
      {
        "id": "ava",
        "type": "lore",
        "relation": "related",
        "auto_generated": true,
        "note_fr": "Lien réciproque automatique",
        "note_en": "Auto-generated reciprocal link"
      },
      {
        "id": "gaish",
        "type": "lore",
        "relation": "related",
        "auto_generated": true,
        "note_fr": "Lien réciproque automatique",
        "note_en": "Auto-generated reciprocal link"
      },
      {
        "id": "himonshe",
        "type": "lore",
        "relation": "related",
        "auto_generated": true,
        "note_fr": "Lien réciproque automatique",
        "note_en": "Auto-generated reciprocal link"
      },
      {
        "id": "malik",
        "type": "lore",
        "relation": "related",
        "auto_generated": true,
        "note_fr": "Lien réciproque automatique",
        "note_en": "Auto-generated reciprocal link"
      },
      {
        "id": "necrit",
        "type": "lore",
        "relation": "related",
        "auto_generated": true,
        "note_fr": "Lien réciproque automatique",
        "note_en": "Auto-generated reciprocal link"
      },
      {
        "id": "rafen",
        "type": "lore",
        "relation": "related",
        "auto_generated": true,
        "note_fr": "Lien réciproque automatique",
        "note_en": "Auto-generated reciprocal link"
      },
      {
        "id": "rhasa-the-sunderer",
        "type": "lore",
        "relation": "related",
        "auto_generated": true,
        "note_fr": "Lien réciproque automatique",
        "note_en": "Auto-generated reciprocal link"
      },
      {
        "id": "sainen-thousand-tailed",
        "type": "lore",
        "relation": "related",
        "auto_generated": true,
        "note_fr": "Lien réciproque automatique",
        "note_en": "Auto-generated reciprocal link"
      }
    ]
  },
  {
    "id": "akali",
    "name": "Akali",
    "thumbnail": "https://ddragon.leagueoflegends.com/cdn/16.8.1/img/champion/Akali.png",
    "factionKey": "ionia",
    "type": "champion",
    "canon": true,
    "version": "16.8.1",
    "related_characters": [
      {
        "id": "kusho",
        "type": "lore",
        "relation": "mentor",
        "auto_generated": false,
        "note_fr": "Ancien mentor",
        "note_en": "Former Mentor"
      },
      {
        "id": "faey",
        "type": "lore",
        "relation": "related",
        "auto_generated": true,
        "note_fr": "Lien réciproque automatique",
        "note_en": "Auto-generated reciprocal link"
      },
      {
        "id": "mayym-jhomen-tethi",
        "type": "lore",
        "relation": "related",
        "auto_generated": true,
        "note_fr": "Lien réciproque automatique",
        "note_en": "Auto-generated reciprocal link"
      }
    ]
  },
  {
    "id": "hwei",
    "name": "Hwei",
    "thumbnail": "https://ddragon.leagueoflegends.com/cdn/16.8.1/img/champion/Hwei.png",
    "factionKey": "ionia",
    "type": "champion",
    "canon": true,
    "version": "16.8.1",
    "related_characters": []
  },
  {
    "id": "irelia",
    "name": "Irelia",
    "thumbnail": "https://ddragon.leagueoflegends.com/cdn/16.8.1/img/champion/Irelia.png",
    "factionKey": "ionia",
    "type": "champion",
    "canon": true,
    "version": "16.8.1",
    "related_characters": [
      {
        "id": "elder_souma",
        "type": "lore",
        "relation": "student",
        "auto_generated": false,
        "note_fr": "Élève",
        "note_en": "Student"
      },
      {
        "id": "karma",
        "type": "champion",
        "relation": "rival",
        "auto_generated": false,
        "note_fr": "Désaccord politique",
        "note_en": "Political disagreement"
      },
      {
        "id": "swain",
        "type": "champion",
        "relation": "nemesis/war",
        "auto_generated": false
      },
      {
        "id": "aurok-glinthorn",
        "type": "lore",
        "relation": "related",
        "auto_generated": true,
        "note_fr": "Lien réciproque automatique",
        "note_en": "Auto-generated reciprocal link"
      },
      {
        "id": "boram-darkwill",
        "type": "lore",
        "relation": "related",
        "auto_generated": true,
        "note_fr": "Lien réciproque automatique",
        "note_en": "Auto-generated reciprocal link"
      },
      {
        "id": "zinneia",
        "type": "lore",
        "relation": "related",
        "auto_generated": true,
        "note_fr": "Lien réciproque automatique",
        "note_en": "Auto-generated reciprocal link"
      }
    ]
  },
  {
    "id": "ivern",
    "name": "Ivern",
    "thumbnail": "https://ddragon.leagueoflegends.com/cdn/16.8.1/img/champion/Ivern.png",
    "factionKey": "ionia",
    "type": "champion",
    "canon": true,
    "version": "16.8.1",
    "related_characters": [
      {
        "id": "daisy",
        "type": "lore",
        "relation": "related",
        "auto_generated": true,
        "note_fr": "Lien réciproque automatique",
        "note_en": "Auto-generated reciprocal link"
      },
      {
        "id": "himonshe",
        "type": "lore",
        "relation": "related",
        "auto_generated": true,
        "note_fr": "Lien réciproque automatique",
        "note_en": "Auto-generated reciprocal link"
      },
      {
        "id": "sainen-thousand-tailed",
        "type": "lore",
        "relation": "related",
        "auto_generated": true,
        "note_fr": "Lien réciproque automatique",
        "note_en": "Auto-generated reciprocal link"
      }
    ]
  },
  {
    "id": "jhin",
    "name": "Jhin",
    "thumbnail": "https://ddragon.leagueoflegends.com/cdn/16.8.1/img/champion/Jhin.png",
    "factionKey": "ionia",
    "type": "champion",
    "canon": true,
    "version": "16.8.1",
    "related_characters": [
      {
        "id": "shen",
        "type": "champion",
        "relation": "nemesis",
        "auto_generated": false,
        "note_fr": "Cible artistique",
        "note_en": "Artistic target"
      },
      {
        "id": "kusho",
        "type": "lore",
        "relation": "nemesis",
        "auto_generated": false
      },
      {
        "id": "broadmane",
        "type": "lore",
        "relation": "related",
        "auto_generated": true,
        "note_fr": "Lien réciproque automatique",
        "note_en": "Auto-generated reciprocal link"
      }
    ]
  },
  {
    "id": "karma",
    "name": "Karma",
    "thumbnail": "https://ddragon.leagueoflegends.com/cdn/16.8.1/img/champion/Karma.png",
    "factionKey": "ionia",
    "type": "champion",
    "canon": true,
    "version": "16.8.1",
    "related_characters": [
      {
        "id": "irelia",
        "type": "champion",
        "relation": "rival",
        "auto_generated": false,
        "note_fr": "Désaccord politique",
        "note_en": "Political disagreement"
      },
      {
        "id": "boram-darkwill",
        "type": "lore",
        "relation": "related",
        "auto_generated": true,
        "note_fr": "Lien réciproque automatique",
        "note_en": "Auto-generated reciprocal link"
      },
      {
        "id": "jakgri",
        "type": "lore",
        "relation": "related",
        "auto_generated": true,
        "note_fr": "Lien réciproque automatique",
        "note_en": "Auto-generated reciprocal link"
      }
    ]
  },
  {
    "id": "kennen",
    "name": "Kennen",
    "thumbnail": "https://ddragon.leagueoflegends.com/cdn/16.8.1/img/champion/Kennen.png",
    "factionKey": "ionia",
    "type": "champion",
    "canon": true,
    "version": "16.8.1",
    "related_characters": [
      {
        "id": "ava",
        "type": "lore",
        "relation": "related",
        "auto_generated": true,
        "note_fr": "Lien réciproque automatique",
        "note_en": "Auto-generated reciprocal link"
      },
      {
        "id": "bhinan",
        "type": "lore",
        "relation": "related",
        "auto_generated": true,
        "note_fr": "Lien réciproque automatique",
        "note_en": "Auto-generated reciprocal link"
      },
      {
        "id": "faey",
        "type": "lore",
        "relation": "related",
        "auto_generated": true,
        "note_fr": "Lien réciproque automatique",
        "note_en": "Auto-generated reciprocal link"
      },
      {
        "id": "masa",
        "type": "lore",
        "relation": "related",
        "auto_generated": true,
        "note_fr": "Lien réciproque automatique",
        "note_en": "Auto-generated reciprocal link"
      },
      {
        "id": "mayym-jhomen-tethi",
        "type": "lore",
        "relation": "related",
        "auto_generated": true,
        "note_fr": "Lien réciproque automatique",
        "note_en": "Auto-generated reciprocal link"
      },
      {
        "id": "rissu",
        "type": "lore",
        "relation": "related",
        "auto_generated": true,
        "note_fr": "Lien réciproque automatique",
        "note_en": "Auto-generated reciprocal link"
      },
      {
        "id": "shadowmaster-lao",
        "type": "lore",
        "relation": "related",
        "auto_generated": true,
        "note_fr": "Lien réciproque automatique",
        "note_en": "Auto-generated reciprocal link"
      }
    ]
  },
  {
    "id": "leesin",
    "name": "Lee Sin",
    "thumbnail": "https://ddragon.leagueoflegends.com/cdn/16.8.1/img/champion/LeeSin.png",
    "factionKey": "ionia",
    "type": "champion",
    "canon": true,
    "version": "16.8.1",
    "related_characters": []
  },
  {
    "id": "lillia",
    "name": "Lillia",
    "thumbnail": "https://ddragon.leagueoflegends.com/cdn/16.8.1/img/champion/Lillia.png",
    "factionKey": "ionia",
    "type": "champion",
    "canon": true,
    "version": "16.8.1",
    "related_characters": [
      {
        "id": "aisha",
        "type": "lore",
        "relation": "related",
        "auto_generated": true,
        "note_fr": "Lien réciproque automatique",
        "note_en": "Auto-generated reciprocal link"
      }
    ]
  },
  {
    "id": "masteryi",
    "name": "Maître Yi",
    "thumbnail": "https://ddragon.leagueoflegends.com/cdn/16.8.1/img/champion/MasterYi.png",
    "factionKey": "ionia",
    "type": "champion",
    "canon": true,
    "version": "16.8.1",
    "related_characters": [
      {
        "id": "monkeyking",
        "type": "champion",
        "relation": "mentor",
        "auto_generated": false,
        "note_fr": "Maître Wuju",
        "note_en": "Wuju Master"
      }
    ]
  },
  {
    "id": "monkeyking",
    "name": "Wukong",
    "thumbnail": "https://ddragon.leagueoflegends.com/cdn/16.8.1/img/champion/MonkeyKing.png",
    "factionKey": "ionia",
    "type": "champion",
    "canon": true,
    "version": "16.8.1",
    "related_characters": [
      {
        "id": "masteryi",
        "type": "champion",
        "relation": "mentor",
        "auto_generated": false,
        "note_fr": "Maître Wuju",
        "note_en": "Wuju Master"
      },
      {
        "id": "ahri",
        "type": "champion",
        "relation": "friend",
        "auto_generated": false,
        "note_fr": "Ami Vastaya",
        "note_en": "Vastaya friend"
      }
    ]
  },
  {
    "id": "rakan",
    "name": "Rakan",
    "thumbnail": "https://ddragon.leagueoflegends.com/cdn/16.8.1/img/champion/Rakan.png",
    "factionKey": "ionia",
    "type": "champion",
    "canon": true,
    "version": "16.8.1",
    "related_characters": [
      {
        "id": "xayah",
        "type": "champion",
        "relation": "lover",
        "auto_generated": false,
        "note_fr": "Amant",
        "note_en": "Lover"
      }
    ]
  },
  {
    "id": "sett",
    "name": "Sett",
    "thumbnail": "https://ddragon.leagueoflegends.com/cdn/16.8.1/img/champion/Sett.png",
    "factionKey": "ionia",
    "type": "champion",
    "canon": true,
    "version": "16.8.1",
    "related_characters": []
  },
  {
    "id": "shen",
    "name": "Shen",
    "thumbnail": "https://ddragon.leagueoflegends.com/cdn/16.8.1/img/champion/Shen.png",
    "factionKey": "ionia",
    "type": "champion",
    "canon": true,
    "version": "16.8.1",
    "related_characters": [
      {
        "id": "jhin",
        "type": "champion",
        "relation": "nemesis",
        "auto_generated": false,
        "note_fr": "Cible artistique",
        "note_en": "Artistic target"
      },
      {
        "id": "kusho",
        "type": "lore",
        "relation": "father",
        "auto_generated": false,
        "note_fr": "Père",
        "note_en": "Father"
      },
      {
        "id": "zed",
        "type": "champion",
        "relation": "rival/ex-brother",
        "auto_generated": false
      },
      {
        "id": "faey",
        "type": "lore",
        "relation": "related",
        "auto_generated": true,
        "note_fr": "Lien réciproque automatique",
        "note_en": "Auto-generated reciprocal link"
      },
      {
        "id": "mayym-jhomen-tethi",
        "type": "lore",
        "relation": "related",
        "auto_generated": true,
        "note_fr": "Lien réciproque automatique",
        "note_en": "Auto-generated reciprocal link"
      }
    ]
  },
  {
    "id": "syndra",
    "name": "Syndra",
    "thumbnail": "https://ddragon.leagueoflegends.com/cdn/16.8.1/img/champion/Syndra.png",
    "factionKey": "ionia",
    "type": "champion",
    "canon": true,
    "version": "16.8.1",
    "related_characters": [
      {
        "id": "kalan",
        "type": "lore",
        "relation": "related",
        "auto_generated": true,
        "note_fr": "Lien réciproque automatique",
        "note_en": "Auto-generated reciprocal link"
      },
      {
        "id": "sirik",
        "type": "lore",
        "relation": "related",
        "auto_generated": true,
        "note_fr": "Lien réciproque automatique",
        "note_en": "Auto-generated reciprocal link"
      },
      {
        "id": "teneff",
        "type": "lore",
        "relation": "related",
        "auto_generated": true,
        "note_fr": "Lien réciproque automatique",
        "note_en": "Auto-generated reciprocal link"
      }
    ]
  },
  {
    "id": "varus",
    "name": "Varus",
    "thumbnail": "https://ddragon.leagueoflegends.com/cdn/16.8.1/img/champion/Varus.png",
    "factionKey": "ionia",
    "type": "champion",
    "canon": true,
    "version": "16.8.1",
    "related_characters": [
      {
        "id": "aatrox",
        "type": "champion",
        "relation": "family/rival",
        "auto_generated": false,
        "note_fr": "Trouve Varus faible.",
        "note_en": "Finds Varus weak."
      },
      {
        "id": "bhinan",
        "type": "lore",
        "relation": "related",
        "auto_generated": true,
        "note_fr": "Lien réciproque automatique",
        "note_en": "Auto-generated reciprocal link"
      },
      {
        "id": "kai",
        "type": "lore",
        "relation": "related",
        "auto_generated": true,
        "note_fr": "Lien réciproque automatique",
        "note_en": "Auto-generated reciprocal link"
      },
      {
        "id": "mihira",
        "type": "lore",
        "relation": "related",
        "auto_generated": true,
        "note_fr": "Lien réciproque automatique",
        "note_en": "Auto-generated reciprocal link"
      },
      {
        "id": "rhaast",
        "type": "lore",
        "relation": "related",
        "auto_generated": true,
        "note_fr": "Lien réciproque automatique",
        "note_en": "Auto-generated reciprocal link"
      },
      {
        "id": "setaka",
        "type": "lore",
        "relation": "related",
        "auto_generated": true,
        "note_fr": "Lien réciproque automatique",
        "note_en": "Auto-generated reciprocal link"
      },
      {
        "id": "valmar",
        "type": "lore",
        "relation": "related",
        "auto_generated": true,
        "note_fr": "Lien réciproque automatique",
        "note_en": "Auto-generated reciprocal link"
      },
      {
        "id": "xolaani",
        "type": "lore",
        "relation": "related",
        "auto_generated": true,
        "note_fr": "Lien réciproque automatique",
        "note_en": "Auto-generated reciprocal link"
      }
    ]
  },
  {
    "id": "xayah",
    "name": "Xayah",
    "thumbnail": "https://ddragon.leagueoflegends.com/cdn/16.8.1/img/champion/Xayah.png",
    "factionKey": "ionia",
    "type": "champion",
    "canon": true,
    "version": "16.8.1",
    "related_characters": [
      {
        "id": "zed",
        "type": "champion",
        "relation": "rival",
        "auto_generated": false,
        "note_fr": "Son ordre menace les Vastaya",
        "note_en": "his order threatens the vastaya"
      },
      {
        "id": "rakan",
        "type": "champion",
        "relation": "lover",
        "auto_generated": false,
        "note_fr": "Amant",
        "note_en": "Lover"
      }
    ]
  },
  {
    "id": "yasuo",
    "name": "Yasuo",
    "thumbnail": "https://ddragon.leagueoflegends.com/cdn/16.8.1/img/champion/Yasuo.png",
    "factionKey": "ionia",
    "type": "champion",
    "canon": true,
    "version": "16.8.1",
    "related_characters": [
      {
        "id": "taliyah",
        "type": "champion",
        "relation": "student",
        "auto_generated": false,
        "note_fr": "Mentor temporaire",
        "note_en": "Temporary mentor"
      },
      {
        "id": "elder_souma",
        "type": "lore",
        "relation": "student",
        "auto_generated": false,
        "note_fr": "Élève",
        "note_en": "Student"
      },
      {
        "id": "yone",
        "type": "champion",
        "relation": "half-brother",
        "auto_generated": false,
        "note_fr": "Demi-frère",
        "note_en": "Half-brother"
      },
      {
        "id": "malik",
        "type": "lore",
        "relation": "related",
        "auto_generated": true,
        "note_fr": "Lien réciproque automatique",
        "note_en": "Auto-generated reciprocal link"
      },
      {
        "id": "necrit",
        "type": "lore",
        "relation": "related",
        "auto_generated": true,
        "note_fr": "Lien réciproque automatique",
        "note_en": "Auto-generated reciprocal link"
      },
      {
        "id": "rafen",
        "type": "lore",
        "relation": "related",
        "auto_generated": true,
        "note_fr": "Lien réciproque automatique",
        "note_en": "Auto-generated reciprocal link"
      },
      {
        "id": "rhasa-the-sunderer",
        "type": "lore",
        "relation": "related",
        "auto_generated": true,
        "note_fr": "Lien réciproque automatique",
        "note_en": "Auto-generated reciprocal link"
      },
      {
        "id": "souma",
        "type": "lore",
        "relation": "related",
        "auto_generated": true,
        "note_fr": "Lien réciproque automatique",
        "note_en": "Auto-generated reciprocal link"
      }
    ]
  },
  {
    "id": "yone",
    "name": "Yone",
    "thumbnail": "https://ddragon.leagueoflegends.com/cdn/16.8.1/img/champion/Yone.png",
    "factionKey": "ionia",
    "type": "champion",
    "canon": true,
    "version": "16.8.1",
    "related_characters": [
      {
        "id": "yasuo",
        "type": "champion",
        "relation": "half-brother",
        "auto_generated": false,
        "note_fr": "Demi-frère",
        "note_en": "Half-brother"
      },
      {
        "id": "souma",
        "type": "lore",
        "relation": "related",
        "auto_generated": true,
        "note_fr": "Lien réciproque automatique",
        "note_en": "Auto-generated reciprocal link"
      }
    ]
  },
  {
    "id": "yunara",
    "name": "Yunara",
    "thumbnail": "https://ddragon.leagueoflegends.com/cdn/16.8.1/img/champion/Yunara.png",
    "factionKey": "ionia",
    "type": "champion",
    "canon": true,
    "version": "16.8.1",
    "related_characters": [
      {
        "id": "bhinan",
        "type": "lore",
        "relation": "related",
        "auto_generated": true,
        "note_fr": "Lien réciproque automatique",
        "note_en": "Auto-generated reciprocal link"
      },
      {
        "id": "jarvan-iii",
        "type": "lore",
        "relation": "related",
        "auto_generated": true,
        "note_fr": "Lien réciproque automatique",
        "note_en": "Auto-generated reciprocal link"
      },
      {
        "id": "praa-the-breachwalker",
        "type": "lore",
        "relation": "related",
        "auto_generated": true,
        "note_fr": "Lien réciproque automatique",
        "note_en": "Auto-generated reciprocal link"
      },
      {
        "id": "rhaast",
        "type": "lore",
        "relation": "related",
        "auto_generated": true,
        "note_fr": "Lien réciproque automatique",
        "note_en": "Auto-generated reciprocal link"
      },
      {
        "id": "shadowmaster-lao",
        "type": "lore",
        "relation": "related",
        "auto_generated": true,
        "note_fr": "Lien réciproque automatique",
        "note_en": "Auto-generated reciprocal link"
      },
      {
        "id": "tianna",
        "type": "lore",
        "relation": "related",
        "auto_generated": true,
        "note_fr": "Lien réciproque automatique",
        "note_en": "Auto-generated reciprocal link"
      },
      {
        "id": "xolaani",
        "type": "lore",
        "relation": "related",
        "auto_generated": true,
        "note_fr": "Lien réciproque automatique",
        "note_en": "Auto-generated reciprocal link"
      }
    ]
  },
  {
    "id": "zed",
    "name": "Zed",
    "thumbnail": "https://ddragon.leagueoflegends.com/cdn/16.8.1/img/champion/Zed.png",
    "factionKey": "ionia",
    "type": "champion",
    "canon": true,
    "version": "16.8.1",
    "related_characters": [
      {
        "id": "xayah",
        "type": "champion",
        "relation": "rival",
        "auto_generated": false,
        "note_fr": "Son ordre menace les Vastaya",
        "note_en": "his order threatens the vastaya"
      },
      {
        "id": "kayn",
        "type": "champion",
        "relation": "student",
        "auto_generated": false,
        "note_fr": "Élève favori / Successeur",
        "note_en": "Favorite student / Successor"
      },
      {
        "id": "kusho",
        "type": "lore",
        "relation": "student",
        "auto_generated": false,
        "note_fr": "Ancien élève",
        "note_en": "Former Student"
      },
      {
        "id": "shen",
        "type": "champion",
        "relation": "rival/ex-brother",
        "auto_generated": false
      },
      {
        "id": "faey",
        "type": "lore",
        "relation": "related",
        "auto_generated": true,
        "note_fr": "Lien réciproque automatique",
        "note_en": "Auto-generated reciprocal link"
      },
      {
        "id": "mayym-jhomen-tethi",
        "type": "lore",
        "relation": "related",
        "auto_generated": true,
        "note_fr": "Lien réciproque automatique",
        "note_en": "Auto-generated reciprocal link"
      },
      {
        "id": "ren-shadowblade",
        "type": "lore",
        "relation": "related",
        "auto_generated": true,
        "note_fr": "Lien réciproque automatique",
        "note_en": "Auto-generated reciprocal link"
      },
      {
        "id": "rhaast",
        "type": "lore",
        "relation": "related",
        "auto_generated": true,
        "note_fr": "Lien réciproque automatique",
        "note_en": "Auto-generated reciprocal link"
      },
      {
        "id": "rissu",
        "type": "lore",
        "relation": "related",
        "auto_generated": true,
        "note_fr": "Lien réciproque automatique",
        "note_en": "Auto-generated reciprocal link"
      },
      {
        "id": "royce",
        "type": "lore",
        "relation": "related",
        "auto_generated": true,
        "note_fr": "Lien réciproque automatique",
        "note_en": "Auto-generated reciprocal link"
      },
      {
        "id": "shi",
        "type": "lore",
        "relation": "related",
        "auto_generated": true,
        "note_fr": "Lien réciproque automatique",
        "note_en": "Auto-generated reciprocal link"
      },
      {
        "id": "ysdra",
        "type": "lore",
        "relation": "related",
        "auto_generated": true,
        "note_fr": "Lien réciproque automatique",
        "note_en": "Auto-generated reciprocal link"
      },
      {
        "id": "yusari",
        "type": "lore",
        "relation": "related",
        "auto_generated": true,
        "note_fr": "Lien réciproque automatique",
        "note_en": "Auto-generated reciprocal link"
      }
    ]
  },
  {
    "id": "adnere",
    "name": "Adnere",
    "thumbnail": "https://wiki.leagueoflegends.com/en-us/images/08IO019-full.png?114b9",
    "factionKey": "ionia",
    "type": "lore",
    "canon": true,
    "related_characters": []
  },
  {
    "id": "aisha",
    "name": "Aisha",
    "thumbnail": "https://wiki.leagueoflegends.com/en-us/images/09IO046-full.png?a49b5",
    "factionKey": "ionia",
    "type": "lore",
    "canon": true,
    "related_characters": [
      {
        "id": "lillia",
        "type": "lore",
        "relation": "mentioned",
        "auto_generated": false
      }
    ]
  },
  {
    "id": "asa-konte",
    "name": "Asa Konte",
    "thumbnail": "https://wiki.leagueoflegends.com/en-us/images/Default_minor_character_image.png?08d2f",
    "factionKey": "ionia",
    "type": "lore",
    "canon": true,
    "related_characters": [
      {
        "id": "riven",
        "type": "lore",
        "relation": "mentioned",
        "auto_generated": false
      }
    ]
  },
  {
    "id": "bingwen",
    "name": "Bingwen",
    "thumbnail": "https://wiki.leagueoflegends.com/en-us/images/07IO014-full.png?9cd57",
    "factionKey": "ionia",
    "type": "lore",
    "canon": true,
    "related_characters": [
      {
        "id": "kolo-the-killer",
        "type": "lore",
        "relation": "mentioned",
        "auto_generated": false
      },
      {
        "id": "lise",
        "type": "lore",
        "relation": "mentioned",
        "auto_generated": false
      },
      {
        "id": "setts-mother",
        "type": "lore",
        "relation": "mentioned",
        "auto_generated": false
      }
    ]
  },
  {
    "id": "bo-yang",
    "name": "Bo Yang",
    "thumbnail": "https://wiki.leagueoflegends.com/en-us/images/Bo_Yang_Render.png?fa3a9",
    "factionKey": "ionia",
    "type": "lore",
    "canon": true,
    "related_characters": [
      {
        "id": "boram-darkwill",
        "type": "lore",
        "relation": "mentioned",
        "auto_generated": false
      },
      {
        "id": "jarvan-iii",
        "type": "lore",
        "relation": "mentioned",
        "auto_generated": false
      },
      {
        "id": "xin-zhao",
        "type": "lore",
        "relation": "mentioned",
        "auto_generated": false
      }
    ]
  },
  {
    "id": "bri",
    "name": "Bri",
    "thumbnail": "https://wiki.leagueoflegends.com/en-us/images/03IO010-full.png?26084",
    "factionKey": "ionia",
    "type": "lore",
    "canon": true,
    "related_characters": [
      {
        "id": "lulu",
        "type": "lore",
        "relation": "mentioned",
        "auto_generated": false
      },
      {
        "id": "pix",
        "type": "lore",
        "relation": "mentioned",
        "auto_generated": false
      },
      {
        "id": "sallow",
        "type": "lore",
        "relation": "mentioned",
        "auto_generated": false
      },
      {
        "id": "trevor-snoozebottom",
        "type": "lore",
        "relation": "mentioned",
        "auto_generated": false
      }
    ]
  },
  {
    "id": "caprian",
    "name": "Caprian",
    "thumbnail": "https://wiki.leagueoflegends.com/en-us/images/Default_minor_character_image.png?08d2f",
    "factionKey": "ionia",
    "type": "lore",
    "canon": true,
    "related_characters": [
      {
        "id": "ambessa",
        "type": "lore",
        "relation": "mentioned",
        "auto_generated": false
      },
      {
        "id": "boram-darkwill",
        "type": "lore",
        "relation": "mentioned",
        "auto_generated": false
      },
      {
        "id": "mion-of-binan",
        "type": "lore",
        "relation": "mentioned",
        "auto_generated": false
      },
      {
        "id": "rell",
        "type": "lore",
        "relation": "mentioned",
        "auto_generated": false
      },
      {
        "id": "rictus",
        "type": "lore",
        "relation": "mentioned",
        "auto_generated": false
      }
    ]
  },
  {
    "id": "daisy",
    "name": "Daisy",
    "thumbnail": "https://wiki.leagueoflegends.com/en-us/images/Ivern_Concept_16.jpg?7f45f",
    "factionKey": "ionia",
    "type": "lore",
    "canon": true,
    "related_characters": [
      {
        "id": "ivern",
        "type": "lore",
        "relation": "mentioned",
        "auto_generated": false
      }
    ]
  },
  {
    "id": "faey",
    "name": "Faey",
    "thumbnail": "https://wiki.leagueoflegends.com/en-us/images/Ionia_The_Bow%2C_and_the_Kunai.jpg?33ec4",
    "factionKey": "ionia",
    "type": "lore",
    "canon": true,
    "related_characters": [
      {
        "id": "akali",
        "type": "lore",
        "relation": "mentioned",
        "auto_generated": false
      },
      {
        "id": "kennen",
        "type": "lore",
        "relation": "mentioned",
        "auto_generated": false
      },
      {
        "id": "kusho",
        "type": "lore",
        "relation": "mentioned",
        "auto_generated": false
      },
      {
        "id": "mayym-jhomen-tethi",
        "type": "lore",
        "relation": "mentioned",
        "auto_generated": false
      },
      {
        "id": "shen",
        "type": "lore",
        "relation": "mentioned",
        "auto_generated": false
      },
      {
        "id": "zed",
        "type": "lore",
        "relation": "mentioned",
        "auto_generated": false
      }
    ]
  },
  {
    "id": "gaish",
    "name": "Gai'sh",
    "thumbnail": "https://wiki.leagueoflegends.com/en-us/images/05IO006T1-full.png?62d28",
    "factionKey": "ionia",
    "type": "lore",
    "canon": true,
    "related_characters": [
      {
        "id": "ahri",
        "type": "lore",
        "relation": "mentioned",
        "auto_generated": false
      },
      {
        "id": "himonshe",
        "type": "lore",
        "relation": "mentioned",
        "auto_generated": false
      },
      {
        "id": "sainen-thousand-tailed",
        "type": "lore",
        "relation": "mentioned",
        "auto_generated": false
      }
    ]
  },
  {
    "id": "heisho",
    "name": "Heisho",
    "thumbnail": "https://wiki.leagueoflegends.com/en-us/images/08IO014-full.png?6cf59",
    "factionKey": "ionia",
    "type": "lore",
    "canon": true,
    "related_characters": []
  },
  {
    "id": "himonshe",
    "name": "Himon'she",
    "thumbnail": "https://wiki.leagueoflegends.com/en-us/images/05IO003-full.png?38866",
    "factionKey": "ionia",
    "type": "lore",
    "canon": true,
    "related_characters": [
      {
        "id": "ahri",
        "type": "lore",
        "relation": "mentioned",
        "auto_generated": false
      },
      {
        "id": "gaish",
        "type": "lore",
        "relation": "mentioned",
        "auto_generated": false
      },
      {
        "id": "ivern",
        "type": "lore",
        "relation": "mentioned",
        "auto_generated": false
      },
      {
        "id": "sainen-thousand-tailed",
        "type": "lore",
        "relation": "mentioned",
        "auto_generated": false
      }
    ]
  },
  {
    "id": "hui-ning",
    "name": "Hui Ning",
    "thumbnail": "https://wiki.leagueoflegends.com/en-us/images/02IO003-full.png?fa3c7",
    "factionKey": "ionia",
    "type": "lore",
    "canon": true,
    "related_characters": [
      {
        "id": "kaiyan",
        "type": "lore",
        "relation": "mentioned",
        "auto_generated": false
      },
      {
        "id": "lee-sin",
        "type": "lore",
        "relation": "mentioned",
        "auto_generated": false
      },
      {
        "id": "ying-yue",
        "type": "lore",
        "relation": "mentioned",
        "auto_generated": false
      }
    ]
  },
  {
    "id": "jakgri",
    "name": "Jakgri",
    "thumbnail": "https://wiki.leagueoflegends.com/en-us/images/Default_minor_character_image.png?08d2f",
    "factionKey": "ionia",
    "type": "lore",
    "canon": true,
    "related_characters": [
      {
        "id": "karma",
        "type": "lore",
        "relation": "mentioned",
        "auto_generated": false
      }
    ]
  },
  {
    "id": "jun",
    "name": "Jun",
    "thumbnail": "https://wiki.leagueoflegends.com/en-us/images/06IO011-full.png?7271c",
    "factionKey": "ionia",
    "type": "lore",
    "canon": true,
    "related_characters": [
      {
        "id": "kayn",
        "type": "lore",
        "relation": "mentioned",
        "auto_generated": false
      },
      {
        "id": "lui",
        "type": "lore",
        "relation": "mentioned",
        "auto_generated": false
      },
      {
        "id": "ting",
        "type": "lore",
        "relation": "mentioned",
        "auto_generated": false
      },
      {
        "id": "xolaani",
        "type": "lore",
        "relation": "mentioned",
        "auto_generated": false
      },
      {
        "id": "yi",
        "type": "lore",
        "relation": "mentioned",
        "auto_generated": false
      }
    ]
  },
  {
    "id": "kai",
    "name": "Kai",
    "thumbnail": "https://wiki.leagueoflegends.com/en-us/images/Varus_HL_pr01.jpg?1667e",
    "factionKey": "ionia",
    "type": "lore",
    "canon": true,
    "related_characters": [
      {
        "id": "udyr",
        "type": "lore",
        "relation": "mentioned",
        "auto_generated": false
      },
      {
        "id": "valmar",
        "type": "lore",
        "relation": "mentioned",
        "auto_generated": false
      },
      {
        "id": "varus",
        "type": "lore",
        "relation": "mentioned",
        "auto_generated": false
      }
    ]
  },
  {
    "id": "kaiyan",
    "name": "Kaiyan",
    "thumbnail": "https://wiki.leagueoflegends.com/en-us/images/02IO004-full.png?24c4e",
    "factionKey": "ionia",
    "type": "lore",
    "canon": true,
    "related_characters": [
      {
        "id": "hui-ning",
        "type": "lore",
        "relation": "mentioned",
        "auto_generated": false
      },
      {
        "id": "lee-sin",
        "type": "lore",
        "relation": "mentioned",
        "auto_generated": false
      },
      {
        "id": "ying-yue",
        "type": "lore",
        "relation": "mentioned",
        "auto_generated": false
      }
    ]
  },
  {
    "id": "kalan",
    "name": "Kalan",
    "thumbnail": "https://wiki.leagueoflegends.com/en-us/images/Syndra_The_Dreaming_Pool.jpg?32959",
    "factionKey": "ionia",
    "type": "lore",
    "canon": true,
    "related_characters": [
      {
        "id": "jericho",
        "type": "lore",
        "relation": "mentioned",
        "auto_generated": false
      },
      {
        "id": "sirik",
        "type": "lore",
        "relation": "mentioned",
        "auto_generated": false
      },
      {
        "id": "soraka",
        "type": "lore",
        "relation": "mentioned",
        "auto_generated": false
      },
      {
        "id": "swain",
        "type": "lore",
        "relation": "mentioned",
        "auto_generated": false
      },
      {
        "id": "syndra",
        "type": "lore",
        "relation": "mentioned",
        "auto_generated": false
      }
    ]
  },
  {
    "id": "kolo-the-killer",
    "name": "Kolo the Killer",
    "thumbnail": "https://wiki.leagueoflegends.com/en-us/images/07IO013-full.png?67850",
    "factionKey": "ionia",
    "type": "lore",
    "canon": true,
    "related_characters": [
      {
        "id": "bingwen",
        "type": "lore",
        "relation": "mentioned",
        "auto_generated": false
      },
      {
        "id": "bull",
        "type": "lore",
        "relation": "mentioned",
        "auto_generated": false
      },
      {
        "id": "dame-the-despoiler",
        "type": "lore",
        "relation": "mentioned",
        "auto_generated": false
      },
      {
        "id": "jack",
        "type": "lore",
        "relation": "mentioned",
        "auto_generated": false
      },
      {
        "id": "mako",
        "type": "lore",
        "relation": "mentioned",
        "auto_generated": false
      },
      {
        "id": "nukkle",
        "type": "lore",
        "relation": "mentioned",
        "auto_generated": false
      },
      {
        "id": "setts-mother",
        "type": "lore",
        "relation": "mentioned",
        "auto_generated": false
      },
      {
        "id": "lise",
        "type": "lore",
        "relation": "related",
        "auto_generated": true,
        "note_fr": "Lien réciproque automatique",
        "note_en": "Auto-generated reciprocal link"
      },
      {
        "id": "smeek",
        "type": "lore",
        "relation": "related",
        "auto_generated": true,
        "note_fr": "Lien réciproque automatique",
        "note_en": "Auto-generated reciprocal link"
      }
    ]
  },
  {
    "id": "lise",
    "name": "Lise",
    "thumbnail": "https://wiki.leagueoflegends.com/en-us/images/07IO009-full.png?d6e01",
    "factionKey": "ionia",
    "type": "lore",
    "canon": true,
    "related_characters": [
      {
        "id": "kolo-the-killer",
        "type": "lore",
        "relation": "mentioned",
        "auto_generated": false
      },
      {
        "id": "meg",
        "type": "lore",
        "relation": "mentioned",
        "auto_generated": false
      },
      {
        "id": "setts-mother",
        "type": "lore",
        "relation": "mentioned",
        "auto_generated": false
      },
      {
        "id": "smeek",
        "type": "lore",
        "relation": "mentioned",
        "auto_generated": false
      },
      {
        "id": "bingwen",
        "type": "lore",
        "relation": "related",
        "auto_generated": true,
        "note_fr": "Lien réciproque automatique",
        "note_en": "Auto-generated reciprocal link"
      }
    ]
  },
  {
    "id": "lui",
    "name": "Lui",
    "thumbnail": "https://wiki.leagueoflegends.com/en-us/images/06IO001-full.png?3ea3a",
    "factionKey": "ionia",
    "type": "lore",
    "canon": true,
    "related_characters": [
      {
        "id": "doran",
        "type": "lore",
        "relation": "mentioned",
        "auto_generated": false
      },
      {
        "id": "jun",
        "type": "lore",
        "relation": "mentioned",
        "auto_generated": false
      },
      {
        "id": "kayn",
        "type": "lore",
        "relation": "mentioned",
        "auto_generated": false
      },
      {
        "id": "ting",
        "type": "lore",
        "relation": "mentioned",
        "auto_generated": false
      },
      {
        "id": "xolaani",
        "type": "lore",
        "relation": "mentioned",
        "auto_generated": false
      },
      {
        "id": "yi",
        "type": "lore",
        "relation": "mentioned",
        "auto_generated": false
      }
    ]
  },
  {
    "id": "masa",
    "name": "Masa",
    "thumbnail": "https://wiki.leagueoflegends.com/en-us/images/05BC046-full.png?227b7",
    "factionKey": "ionia",
    "type": "lore",
    "canon": true,
    "related_characters": [
      {
        "id": "kennen",
        "type": "lore",
        "relation": "mentioned",
        "auto_generated": false
      },
      {
        "id": "rissu",
        "type": "lore",
        "relation": "mentioned",
        "auto_generated": false
      }
    ]
  },
  {
    "id": "mayym-jhomen-tethi",
    "name": "Mayym Jhomen Tethi",
    "thumbnail": "https://wiki.leagueoflegends.com/en-us/images/Default_minor_character_image.png?08d2f",
    "factionKey": "ionia",
    "type": "lore",
    "canon": true,
    "related_characters": [
      {
        "id": "akali",
        "type": "lore",
        "relation": "mentioned",
        "auto_generated": false
      },
      {
        "id": "faey",
        "type": "lore",
        "relation": "mentioned",
        "auto_generated": false
      },
      {
        "id": "kennen",
        "type": "lore",
        "relation": "mentioned",
        "auto_generated": false
      },
      {
        "id": "kusho",
        "type": "lore",
        "relation": "mentioned",
        "auto_generated": false
      },
      {
        "id": "shen",
        "type": "lore",
        "relation": "mentioned",
        "auto_generated": false
      },
      {
        "id": "zed",
        "type": "lore",
        "relation": "mentioned",
        "auto_generated": false
      }
    ]
  },
  {
    "id": "meg",
    "name": "Meg",
    "thumbnail": "https://wiki.leagueoflegends.com/en-us/images/07IO019-full.png?e0ada",
    "factionKey": "ionia",
    "type": "lore",
    "canon": true,
    "related_characters": [
      {
        "id": "lani",
        "type": "lore",
        "relation": "mentioned",
        "auto_generated": false
      },
      {
        "id": "lise",
        "type": "lore",
        "relation": "mentioned",
        "auto_generated": false
      },
      {
        "id": "miel",
        "type": "lore",
        "relation": "mentioned",
        "auto_generated": false
      },
      {
        "id": "setts-mother",
        "type": "lore",
        "relation": "mentioned",
        "auto_generated": false
      },
      {
        "id": "smeek",
        "type": "lore",
        "relation": "mentioned",
        "auto_generated": false
      }
    ]
  },
  {
    "id": "minah-swiftfoot",
    "name": "Minah Swiftfoot",
    "thumbnail": "https://wiki.leagueoflegends.com/en-us/images/01IO033-full.png?e9733",
    "factionKey": "ionia",
    "type": "lore",
    "canon": true,
    "related_characters": []
  },
  {
    "id": "mion-of-binan",
    "name": "Lady Mion of Binan",
    "thumbnail": "https://wiki.leagueoflegends.com/en-us/images/Mion_Render.png?54ce6",
    "factionKey": "ionia",
    "type": "lore",
    "canon": true,
    "related_characters": [
      {
        "id": "ambessa",
        "type": "lore",
        "relation": "mentioned",
        "auto_generated": false
      },
      {
        "id": "boram-darkwill",
        "type": "lore",
        "relation": "mentioned",
        "auto_generated": false
      },
      {
        "id": "leblanc",
        "type": "lore",
        "relation": "mentioned",
        "auto_generated": false
      },
      {
        "id": "mel",
        "type": "lore",
        "relation": "mentioned",
        "auto_generated": false
      },
      {
        "id": "rictus",
        "type": "lore",
        "relation": "mentioned",
        "auto_generated": false
      },
      {
        "id": "caprian",
        "type": "lore",
        "relation": "related",
        "auto_generated": true,
        "note_fr": "Lien réciproque automatique",
        "note_en": "Auto-generated reciprocal link"
      }
    ]
  },
  {
    "id": "ren-shadowblade",
    "name": "Ren Shadowblade",
    "thumbnail": "https://wiki.leagueoflegends.com/en-us/images/06IO025-full.png?c3b2c",
    "factionKey": "ionia",
    "type": "lore",
    "canon": true,
    "related_characters": [
      {
        "id": "kayn",
        "type": "lore",
        "relation": "mentioned",
        "auto_generated": false
      },
      {
        "id": "rhaast",
        "type": "lore",
        "relation": "mentioned",
        "auto_generated": false
      },
      {
        "id": "royce",
        "type": "lore",
        "relation": "mentioned",
        "auto_generated": false
      },
      {
        "id": "xolaani",
        "type": "lore",
        "relation": "mentioned",
        "auto_generated": false
      },
      {
        "id": "ysdra",
        "type": "lore",
        "relation": "mentioned",
        "auto_generated": false
      },
      {
        "id": "zed",
        "type": "lore",
        "relation": "mentioned",
        "auto_generated": false
      }
    ]
  },
  {
    "id": "rissu",
    "name": "Rissu",
    "thumbnail": "https://wiki.leagueoflegends.com/en-us/images/05BC127-full.png?f23ed",
    "factionKey": "ionia",
    "type": "lore",
    "canon": true,
    "related_characters": [
      {
        "id": "kennen",
        "type": "lore",
        "relation": "mentioned",
        "auto_generated": false
      },
      {
        "id": "zed",
        "type": "lore",
        "relation": "mentioned",
        "auto_generated": false
      },
      {
        "id": "masa",
        "type": "lore",
        "relation": "related",
        "auto_generated": true,
        "note_fr": "Lien réciproque automatique",
        "note_en": "Auto-generated reciprocal link"
      }
    ]
  },
  {
    "id": "royce",
    "name": "Royce",
    "thumbnail": "https://wiki.leagueoflegends.com/en-us/images/06NX019-full.png?71620",
    "factionKey": "ionia",
    "type": "lore",
    "canon": true,
    "related_characters": [
      {
        "id": "boram-darkwill",
        "type": "lore",
        "relation": "mentioned",
        "auto_generated": false
      },
      {
        "id": "kayn",
        "type": "lore",
        "relation": "mentioned",
        "auto_generated": false
      },
      {
        "id": "ren-shadowblade",
        "type": "lore",
        "relation": "mentioned",
        "auto_generated": false
      },
      {
        "id": "rhaast",
        "type": "lore",
        "relation": "mentioned",
        "auto_generated": false
      },
      {
        "id": "swain",
        "type": "lore",
        "relation": "mentioned",
        "auto_generated": false
      },
      {
        "id": "ting",
        "type": "lore",
        "relation": "mentioned",
        "auto_generated": false
      },
      {
        "id": "xolaani",
        "type": "lore",
        "relation": "mentioned",
        "auto_generated": false
      },
      {
        "id": "ysdra",
        "type": "lore",
        "relation": "mentioned",
        "auto_generated": false
      },
      {
        "id": "zed",
        "type": "lore",
        "relation": "mentioned",
        "auto_generated": false
      }
    ]
  },
  {
    "id": "sainen-thousand-tailed",
    "name": "Sai'nen Thousand-Tailed",
    "thumbnail": "https://wiki.leagueoflegends.com/en-us/images/05IO007-full.png?1a027",
    "factionKey": "ionia",
    "type": "lore",
    "canon": true,
    "related_characters": [
      {
        "id": "ahri",
        "type": "lore",
        "relation": "mentioned",
        "auto_generated": false
      },
      {
        "id": "gaish",
        "type": "lore",
        "relation": "mentioned",
        "auto_generated": false
      },
      {
        "id": "himonshe",
        "type": "lore",
        "relation": "mentioned",
        "auto_generated": false
      },
      {
        "id": "ivern",
        "type": "lore",
        "relation": "mentioned",
        "auto_generated": false
      }
    ]
  },
  {
    "id": "setts-mother",
    "name": "Sett's mother",
    "thumbnail": "https://wiki.leagueoflegends.com/en-us/images/Sett_Concept_06.jpg?9033b",
    "factionKey": "ionia",
    "type": "lore",
    "canon": true,
    "related_characters": [
      {
        "id": "bingwen",
        "type": "lore",
        "relation": "related",
        "auto_generated": true,
        "note_fr": "Lien réciproque automatique",
        "note_en": "Auto-generated reciprocal link"
      },
      {
        "id": "bull",
        "type": "lore",
        "relation": "related",
        "auto_generated": true,
        "note_fr": "Lien réciproque automatique",
        "note_en": "Auto-generated reciprocal link"
      },
      {
        "id": "dame-the-despoiler",
        "type": "lore",
        "relation": "related",
        "auto_generated": true,
        "note_fr": "Lien réciproque automatique",
        "note_en": "Auto-generated reciprocal link"
      },
      {
        "id": "jack",
        "type": "lore",
        "relation": "related",
        "auto_generated": true,
        "note_fr": "Lien réciproque automatique",
        "note_en": "Auto-generated reciprocal link"
      },
      {
        "id": "kolo-the-killer",
        "type": "lore",
        "relation": "related",
        "auto_generated": true,
        "note_fr": "Lien réciproque automatique",
        "note_en": "Auto-generated reciprocal link"
      },
      {
        "id": "lise",
        "type": "lore",
        "relation": "related",
        "auto_generated": true,
        "note_fr": "Lien réciproque automatique",
        "note_en": "Auto-generated reciprocal link"
      },
      {
        "id": "mako",
        "type": "lore",
        "relation": "related",
        "auto_generated": true,
        "note_fr": "Lien réciproque automatique",
        "note_en": "Auto-generated reciprocal link"
      },
      {
        "id": "meg",
        "type": "lore",
        "relation": "related",
        "auto_generated": true,
        "note_fr": "Lien réciproque automatique",
        "note_en": "Auto-generated reciprocal link"
      },
      {
        "id": "nukkle",
        "type": "lore",
        "relation": "related",
        "auto_generated": true,
        "note_fr": "Lien réciproque automatique",
        "note_en": "Auto-generated reciprocal link"
      },
      {
        "id": "ol-babs",
        "type": "lore",
        "relation": "related",
        "auto_generated": true,
        "note_fr": "Lien réciproque automatique",
        "note_en": "Auto-generated reciprocal link"
      },
      {
        "id": "smeek",
        "type": "lore",
        "relation": "related",
        "auto_generated": true,
        "note_fr": "Lien réciproque automatique",
        "note_en": "Auto-generated reciprocal link"
      }
    ]
  },
  {
    "id": "shadowmaster-lao",
    "name": "Shadowmaster Lao",
    "thumbnail": "https://wiki.leagueoflegends.com/en-us/images/Default_minor_character_image.png?08d2f",
    "factionKey": "ionia",
    "type": "lore",
    "canon": true,
    "related_characters": [
      {
        "id": "bhinan",
        "type": "lore",
        "relation": "mentioned",
        "auto_generated": false
      },
      {
        "id": "kennen",
        "type": "lore",
        "relation": "mentioned",
        "auto_generated": false
      },
      {
        "id": "xolaani",
        "type": "lore",
        "relation": "mentioned",
        "auto_generated": false
      },
      {
        "id": "yunara",
        "type": "lore",
        "relation": "mentioned",
        "auto_generated": false
      }
    ]
  },
  {
    "id": "shava-konte",
    "name": "Shava Konte",
    "thumbnail": "https://wiki.leagueoflegends.com/en-us/images/Default_minor_character_image.png?08d2f",
    "factionKey": "ionia",
    "type": "lore",
    "canon": true,
    "related_characters": [
      {
        "id": "riven",
        "type": "lore",
        "relation": "mentioned",
        "auto_generated": false
      }
    ]
  },
  {
    "id": "shi",
    "name": "Shi",
    "thumbnail": "https://wiki.leagueoflegends.com/en-us/images/01IO027-full.png?82258",
    "factionKey": "ionia",
    "type": "lore",
    "canon": true,
    "related_characters": [
      {
        "id": "kayn",
        "type": "lore",
        "relation": "mentioned",
        "auto_generated": false
      },
      {
        "id": "shadow-assassin",
        "type": "lore",
        "relation": "mentioned",
        "auto_generated": false
      },
      {
        "id": "zed",
        "type": "lore",
        "relation": "mentioned",
        "auto_generated": false
      }
    ]
  },
  {
    "id": "sirik",
    "name": "Sirik",
    "thumbnail": "https://wiki.leagueoflegends.com/en-us/images/Syndra_The_Dreaming_Pool.jpg?32959",
    "factionKey": "ionia",
    "type": "lore",
    "canon": true,
    "related_characters": [
      {
        "id": "kalan",
        "type": "lore",
        "relation": "mentioned",
        "auto_generated": false
      },
      {
        "id": "sky-young",
        "type": "lore",
        "relation": "mentioned",
        "auto_generated": false
      },
      {
        "id": "syndra",
        "type": "lore",
        "relation": "mentioned",
        "auto_generated": false
      }
    ]
  },
  {
    "id": "smeek",
    "name": "Smeek",
    "thumbnail": "https://wiki.leagueoflegends.com/en-us/images/07IO012-full.png?7b8a3",
    "factionKey": "ionia",
    "type": "lore",
    "canon": true,
    "related_characters": [
      {
        "id": "jack",
        "type": "lore",
        "relation": "mentioned",
        "auto_generated": false
      },
      {
        "id": "kolo-the-killer",
        "type": "lore",
        "relation": "mentioned",
        "auto_generated": false
      },
      {
        "id": "lise",
        "type": "lore",
        "relation": "mentioned",
        "auto_generated": false
      },
      {
        "id": "meg",
        "type": "lore",
        "relation": "mentioned",
        "auto_generated": false
      },
      {
        "id": "samira",
        "type": "lore",
        "relation": "mentioned",
        "auto_generated": false
      },
      {
        "id": "setts-mother",
        "type": "lore",
        "relation": "mentioned",
        "auto_generated": false
      }
    ]
  },
  {
    "id": "souma",
    "name": "Souma",
    "thumbnail": "https://wiki.leagueoflegends.com/en-us/images/ElderSouma.png?4ddf2",
    "factionKey": "ionia",
    "type": "lore",
    "canon": true,
    "related_characters": [
      {
        "id": "riven",
        "type": "lore",
        "relation": "mentioned",
        "auto_generated": false
      },
      {
        "id": "yasuo",
        "type": "lore",
        "relation": "mentioned",
        "auto_generated": false
      },
      {
        "id": "yone",
        "type": "lore",
        "relation": "mentioned",
        "auto_generated": false
      }
    ]
  },
  {
    "id": "ting",
    "name": "Ting",
    "thumbnail": "https://wiki.leagueoflegends.com/en-us/images/06IO014-full.png?67647",
    "factionKey": "ionia",
    "type": "lore",
    "canon": true,
    "related_characters": [
      {
        "id": "jun",
        "type": "lore",
        "relation": "mentioned",
        "auto_generated": false
      },
      {
        "id": "kayn",
        "type": "lore",
        "relation": "mentioned",
        "auto_generated": false
      },
      {
        "id": "lui",
        "type": "lore",
        "relation": "mentioned",
        "auto_generated": false
      },
      {
        "id": "royce",
        "type": "lore",
        "relation": "mentioned",
        "auto_generated": false
      },
      {
        "id": "wukong",
        "type": "lore",
        "relation": "mentioned",
        "auto_generated": false
      },
      {
        "id": "xolaani",
        "type": "lore",
        "relation": "mentioned",
        "auto_generated": false
      },
      {
        "id": "yi",
        "type": "lore",
        "relation": "mentioned",
        "auto_generated": false
      }
    ]
  },
  {
    "id": "trisk",
    "name": "Trisk",
    "thumbnail": "https://wiki.leagueoflegends.com/en-us/images/06NX023-full.png?e3670",
    "factionKey": "ionia",
    "type": "lore",
    "canon": true,
    "related_characters": [
      {
        "id": "breshi",
        "type": "lore",
        "relation": "mentioned",
        "auto_generated": false
      },
      {
        "id": "chaska",
        "type": "lore",
        "relation": "mentioned",
        "auto_generated": false
      },
      {
        "id": "fireth",
        "type": "lore",
        "relation": "mentioned",
        "auto_generated": false
      },
      {
        "id": "jax",
        "type": "lore",
        "relation": "mentioned",
        "auto_generated": false
      },
      {
        "id": "pesh",
        "type": "lore",
        "relation": "mentioned",
        "auto_generated": false
      },
      {
        "id": "fireth-reaper-of-the-sands",
        "type": "lore",
        "relation": "related",
        "auto_generated": true,
        "note_fr": "Lien réciproque automatique",
        "note_en": "Auto-generated reciprocal link"
      }
    ]
  },
  {
    "id": "valmar",
    "name": "Valmar",
    "thumbnail": "https://wiki.leagueoflegends.com/en-us/images/Varus_HL_pr01.jpg?1667e",
    "factionKey": "ionia",
    "type": "lore",
    "canon": true,
    "related_characters": [
      {
        "id": "kai",
        "type": "lore",
        "relation": "mentioned",
        "auto_generated": false
      },
      {
        "id": "udyr",
        "type": "lore",
        "relation": "mentioned",
        "auto_generated": false
      },
      {
        "id": "varus",
        "type": "lore",
        "relation": "mentioned",
        "auto_generated": false
      }
    ]
  },
  {
    "id": "ying-yue",
    "name": "Ying Yue",
    "thumbnail": "https://wiki.leagueoflegends.com/en-us/images/02IO001-full.png?5afe1",
    "factionKey": "ionia",
    "type": "lore",
    "canon": true,
    "related_characters": [
      {
        "id": "hui-ning",
        "type": "lore",
        "relation": "mentioned",
        "auto_generated": false
      },
      {
        "id": "kaiyan",
        "type": "lore",
        "relation": "mentioned",
        "auto_generated": false
      },
      {
        "id": "lee-sin",
        "type": "lore",
        "relation": "mentioned",
        "auto_generated": false
      }
    ]
  },
  {
    "id": "ysdra",
    "name": "Ysdra",
    "thumbnail": "https://wiki.leagueoflegends.com/en-us/images/06SI006-full.png?a8efc",
    "factionKey": "ionia",
    "type": "lore",
    "canon": true,
    "related_characters": [
      {
        "id": "kayn",
        "type": "lore",
        "relation": "mentioned",
        "auto_generated": false
      },
      {
        "id": "ren-shadowblade",
        "type": "lore",
        "relation": "mentioned",
        "auto_generated": false
      },
      {
        "id": "rhaast",
        "type": "lore",
        "relation": "mentioned",
        "auto_generated": false
      },
      {
        "id": "royce",
        "type": "lore",
        "relation": "mentioned",
        "auto_generated": false
      },
      {
        "id": "xolaani",
        "type": "lore",
        "relation": "mentioned",
        "auto_generated": false
      },
      {
        "id": "zed",
        "type": "lore",
        "relation": "mentioned",
        "auto_generated": false
      }
    ]
  },
  {
    "id": "yusari",
    "name": "Yusari",
    "thumbnail": "https://wiki.leagueoflegends.com/en-us/images/01IO048-full.png?59581",
    "factionKey": "ionia",
    "type": "lore",
    "canon": true,
    "related_characters": [
      {
        "id": "kayn",
        "type": "lore",
        "relation": "mentioned",
        "auto_generated": false
      },
      {
        "id": "zed",
        "type": "lore",
        "relation": "mentioned",
        "auto_generated": false
      }
    ]
  },
  {
    "id": "zinneia",
    "name": "Zinneia",
    "thumbnail": "https://wiki.leagueoflegends.com/en-us/images/04IO002-full.png?2c856",
    "factionKey": "ionia",
    "type": "lore",
    "canon": true,
    "related_characters": [
      {
        "id": "irelia",
        "type": "lore",
        "relation": "mentioned",
        "auto_generated": false
      },
      {
        "id": "aurok-glinthorn",
        "type": "lore",
        "relation": "related",
        "auto_generated": true,
        "note_fr": "Lien réciproque automatique",
        "note_en": "Auto-generated reciprocal link"
      }
    ]
  }
]