{
  "id": "edvin-cortain",
  "name": "Edvin Cortain",
  "origin_region": "noxus",
  "region": "noxus",
  "faction": [
    "noxus"
  ],
  "universe": [
    "runeterra-prime"
  ],
  "gender": "unknown",
  "species": [
    "human"
  ],
  "status": "unknown",
  "power_source": "blood-magic",
  "image": "https://wiki.leagueoflegends.com/en-us/images/01NX048-full.png?30579",
  "created_at": "2026-03-31T19:36:49.410953+00:00",
  "description_en": "Edvin Cortain is a member of Crimson Circle and a noble, who studies hemomancy for influence. Edvin is known to host many parties which are attended by Vladimir. LeBlanc considers him to be a \"buffoon.\"",
  "description_fr": "Edvin Cortain est membre du Crimson Circle et un noble qui étudie l'hémomancie pour son influence. Edvin est connu pour organiser de nombreuses fêtes auxquelles participe Vladimir. LeBlanc le considère comme un « bouffon ».",
  "related_characters": [
    "Clara",
    "Kye",
    "LeBlanc",
    "Ophelia Noradi",
    "Vladimir"
  ]
}