[
  {
    "id": "alune",
    "name": "Alune",
    "image": null
  },
  {
    "id": "amara",
    "name": "Amara",
    "image": null
  },
  {
    "id": "amoline",
    "name": "Amoline",
    "image": null
  },
  {
    "id": "anaakca",
    "name": "Anaakca",
    "image": null
  },
  {
    "id": "arcturus_j_durand",
    "name": "Arcturus J. Durand",
    "image": null
  },
  {
    "id": "arrel",
    "name": "Arrel",
    "image": null
  },
  {
    "id": "ashlesh",
    "name": "Ashlesh",
    "image": null
  },
  {
    "id": "ava",
    "name": "Ava",
    "image": null
  },
  {
    "id": "avarosa",
    "name": "Avarosa",
    "image": null
  },
  {
    "id": "azizi",
    "name": "Azizi",
    "image": null
  },
  {
    "id": "baalkux",
    "name": "Baalkux",
    "image": null
  },
  {
    "id": "babette",
    "name": "Babette",
    "image": null
  },
  {
    "id": "benzo",
    "name": "Benzo",
    "image": null
  },
  {
    "id": "bhinan",
    "name": "Bhinan",
    "image": null
  },
  {
    "id": "billingsworth",
    "name": "Billingsworth",
    "image": null
  },
  {
    "id": "bo",
    "name": "Bo",
    "image": null
  },
  {
    "id": "bolbok",
    "name": "Bolbok",
    "image": null
  },
  {
    "id": "boram",
    "name": "Boram",
    "image": null
  },
  {
    "id": "boram_darkwill",
    "name": "Boram Darkwill",
    "image": null
  },
  {
    "id": "brannin",
    "name": "Brannin",
    "image": null
  },
  {
    "id": "brock",
    "name": "Brock",
    "image": null
  },
  {
    "id": "brokvar",
    "name": "Brokvar",
    "image": null
  },
  {
    "id": "cassandra",
    "name": "Cassandra",
    "image": null
  },
  {
    "id": "chip",
    "name": "Chip",
    "image": null
  },
  {
    "id": "choncc",
    "name": "Choncc",
    "image": null
  },
  {
    "id": "chross",
    "name": "Chross",
    "image": null
  },
  {
    "id": "cinquieme_darkin",
    "name": "Cinquième Darkin",
    "image": null
  },
  {
    "id": "cithria",
    "name": "Cithria",
    "image": null
  },
  {
    "id": "claggor",
    "name": "Claggor",
    "image": null
  },
  {
    "id": "daisy",
    "name": "Daisy",
    "image": null
  },
  {
    "id": "darkwill",
    "name": "Darkwill",
    "image": null
  },
  {
    "id": "deckard",
    "name": "Deckard",
    "image": null
  },
  {
    "id": "doran",
    "name": "Doran",
    "image": null
  },
  {
    "id": "dr",
    "name": "Dr.",
    "image": null
  },
  {
    "id": "dragon",
    "name": "Dragon",
    "image": null
  },
  {
    "id": "elder",
    "name": "Elder",
    "image": null
  },
  {
    "id": "elder_souma",
    "name": "Elder Souma",
    "image": null
  },
  {
    "id": "eldred",
    "name": "Eldred",
    "image": null
  },
  {
    "id": "elora",
    "name": "Elora",
    "image": null
  },
  {
    "id": "erath",
    "name": "Erath",
    "image": null
  },
  {
    "id": "erzsi",
    "name": "Erzsi",
    "image": null
  },
  {
    "id": "eve",
    "name": "Eve",
    "image": null
  },
  {
    "id": "faey",
    "name": "Faey",
    "image": null
  },
  {
    "id": "farron",
    "name": "Farron",
    "image": null
  },
  {
    "id": "felicia",
    "name": "Felicia",
    "image": null
  },
  {
    "id": "finn",
    "name": "Finn",
    "image": null
  },
  {
    "id": "gert",
    "name": "Gert",
    "image": null
  },
  {
    "id": "gorgeous",
    "name": "Gorgeous",
    "image": null
  },
  {
    "id": "granth",
    "name": "Granth",
    "image": null
  },
  {
    "id": "grayson",
    "name": "Grayson",
    "image": null
  },
  {
    "id": "gregori",
    "name": "Gregori",
    "image": null
  },
  {
    "id": "grena",
    "name": "Grena",
    "image": null
  },
  {
    "id": "gustove",
    "name": "Gustove",
    "image": null
  },
  {
    "id": "hamlet",
    "name": "Hamlet",
    "image": null
  },
  {
    "id": "harold",
    "name": "Harold",
    "image": null
  },
  {
    "id": "heenot",
    "name": "Heenot",
    "image": null
  },
  {
    "id": "helnr",
    "name": "Helnr",
    "image": null
  },
  {
    "id": "horazi",
    "name": "Horazi",
    "image": null
  },
  {
    "id": "hoskel",
    "name": "Hoskel",
    "image": null
  },
  {
    "id": "huck",
    "name": "Huck",
    "image": null
  },
  {
    "id": "indari",
    "name": "Indari",
    "image": null
  },
  {
    "id": "isha",
    "name": "Isha",
    "image": null
  },
  {
    "id": "isolde",
    "name": "Isolde",
    "image": null
  },
  {
    "id": "iula",
    "name": "Iula",
    "image": null
  },
  {
    "id": "jack",
    "name": "Jack",
    "image": null
  },
  {
    "id": "jago",
    "name": "Jago",
    "image": null
  },
  {
    "id": "januk",
    "name": "Januk",
    "image": null
  },
  {
    "id": "jarvan_iii",
    "name": "Jarvan III",
    "image": null
  },
  {
    "id": "jendakaya",
    "name": "Jenda'kaya",
    "image": null
  },
  {
    "id": "jericho",
    "name": "Jericho",
    "image": null
  },
  {
    "id": "joraal",
    "name": "Joraal",
    "image": null
  },
  {
    "id": "jules",
    "name": "Jules",
    "image": null
  },
  {
    "id": "kai",
    "name": "Kai",
    "image": null
  },
  {
    "id": "kalan",
    "name": "Kalan",
    "image": null
  },
  {
    "id": "kalkia",
    "name": "Kalkia",
    "image": null
  },
  {
    "id": "kino",
    "name": "Kino",
    "image": null
  },
  {
    "id": "kobuko",
    "name": "Kobuko",
    "image": null
  },
  {
    "id": "kusho",
    "name": "Kusho",
    "image": null
  },
  {
    "id": "lamb",
    "name": "Lamb",
    "image": null
  },
  {
    "id": "layka",
    "name": "Layka",
    "image": null
  },
  {
    "id": "ledros",
    "name": "Ledros",
    "image": null
  },
  {
    "id": "lest",
    "name": "Lest",
    "image": null
  },
  {
    "id": "loris",
    "name": "Loris",
    "image": null
  },
  {
    "id": "maalcrom",
    "name": "Maalcrom",
    "image": null
  },
  {
    "id": "maddie",
    "name": "Maddie",
    "image": null
  },
  {
    "id": "malik",
    "name": "Malik",
    "image": null
  },
  {
    "id": "man",
    "name": "Man",
    "image": null
  },
  {
    "id": "mantaire",
    "name": "Mantaire",
    "image": null
  },
  {
    "id": "marcus",
    "name": "Marcus",
    "image": null
  },
  {
    "id": "margot",
    "name": "Margot",
    "image": null
  },
  {
    "id": "marit",
    "name": "Marit",
    "image": null
  },
  {
    "id": "mayym",
    "name": "Mayym",
    "image": null
  },
  {
    "id": "merrek",
    "name": "Merrek",
    "image": null
  },
  {
    "id": "mihira",
    "name": "Mihira",
    "image": null
  },
  {
    "id": "mion",
    "name": "Mion",
    "image": null
  },
  {
    "id": "molediver",
    "name": "Molediver",
    "image": null
  },
  {
    "id": "mylo",
    "name": "Mylo",
    "image": null
  },
  {
    "id": "nagakabouros",
    "name": "Nagakabouros",
    "image": null
  },
  {
    "id": "naganeka",
    "name": "Naganeka",
    "image": null
  },
  {
    "id": "necrit",
    "name": "Necrit",
    "image": null
  },
  {
    "id": "norra",
    "name": "Norra",
    "image": null
  },
  {
    "id": "nunu",
    "name": "Nunu",
    "image": null
  },
  {
    "id": "nyam",
    "name": "Nyam",
    "image": null
  },
  {
    "id": "pengu",
    "name": "Pengu",
    "image": null
  },
  {
    "id": "pim",
    "name": "Pim",
    "image": null
  },
  {
    "id": "praa",
    "name": "Praa",
    "image": null
  },
  {
    "id": "rafen",
    "name": "Rafen",
    "image": null
  },
  {
    "id": "ran",
    "name": "Ran",
    "image": null
  },
  {
    "id": "ren",
    "name": "Ren",
    "image": null
  },
  {
    "id": "renni",
    "name": "Renni",
    "image": null
  },
  {
    "id": "rhaast",
    "name": "Rhaast",
    "image": null
  },
  {
    "id": "rictus",
    "name": "Rictus",
    "image": null
  },
  {
    "id": "rudo",
    "name": "Rudo",
    "image": null
  },
  {
    "id": "salo",
    "name": "Salo",
    "image": null
  },
  {
    "id": "scar",
    "name": "Scar",
    "image": null
  },
  {
    "id": "serylda",
    "name": "Serylda",
    "image": null
  },
  {
    "id": "setaka",
    "name": "Setaka",
    "image": null
  },
  {
    "id": "sevika",
    "name": "Sevika",
    "image": null
  },
  {
    "id": "shadya",
    "name": "Shadya",
    "image": null
  },
  {
    "id": "shoola",
    "name": "Shoola",
    "image": null
  },
  {
    "id": "silco",
    "name": "Silco",
    "image": null
  },
  {
    "id": "sirik",
    "name": "Sirik",
    "image": null
  },
  {
    "id": "skaarl",
    "name": "Skaarl",
    "image": null
  },
  {
    "id": "sky",
    "name": "Sky",
    "image": null
  },
  {
    "id": "smeech",
    "name": "Smeech",
    "image": null
  },
  {
    "id": "sohm",
    "name": "Sohm",
    "image": null
  },
  {
    "id": "souma",
    "name": "Souma",
    "image": null
  },
  {
    "id": "stanwick",
    "name": "Stanwick",
    "image": null
  },
  {
    "id": "steb",
    "name": "Steb",
    "image": null
  },
  {
    "id": "styraatu",
    "name": "Styraatu",
    "image": null
  },
  {
    "id": "taarosh",
    "name": "Taarosh",
    "image": null
  },
  {
    "id": "tamara",
    "name": "Tamara",
    "image": null
  },
  {
    "id": "teneff",
    "name": "Teneff",
    "image": null
  },
  {
    "id": "thieram",
    "name": "Thieram",
    "image": null
  },
  {
    "id": "thorne",
    "name": "Thorne",
    "image": null
  },
  {
    "id": "tiana_crownguard",
    "name": "Tiana Crownguard",
    "image": null
  },
  {
    "id": "tianna",
    "name": "Tianna",
    "image": null
  },
  {
    "id": "tibbers",
    "name": "Tibbers",
    "image": null
  },
  {
    "id": "tifalenji",
    "name": "Tifalenji",
    "image": null
  },
  {
    "id": "tobias",
    "name": "Tobias",
    "image": null
  },
  {
    "id": "tommy",
    "name": "Tommy",
    "image": null
  },
  {
    "id": "tope",
    "name": "Tope",
    "image": null
  },
  {
    "id": "tyari",
    "name": "Tyari",
    "image": null
  },
  {
    "id": "tybaulk",
    "name": "Tybaulk",
    "image": null
  },
  {
    "id": "tyrus",
    "name": "Tyrus",
    "image": null
  },
  {
    "id": "urkath",
    "name": "Urkath",
    "image": null
  },
  {
    "id": "valmar",
    "name": "Valmar",
    "image": null
  },
  {
    "id": "valor",
    "name": "Valor",
    "image": null
  },
  {
    "id": "vander",
    "name": "Vander",
    "image": null
  },
  {
    "id": "vennix",
    "name": "Vennix",
    "image": null
  },
  {
    "id": "verne",
    "name": "Verne",
    "image": null
  },
  {
    "id": "vilemaw",
    "name": "Vilemaw",
    "image": null
  },
  {
    "id": "vrynna",
    "name": "Vrynna",
    "image": null
  },
  {
    "id": "warden",
    "name": "Warden",
    "image": null
  },
  {
    "id": "whisker",
    "name": "Whisker",
    "image": null
  },
  {
    "id": "willump",
    "name": "Willump",
    "image": null
  },
  {
    "id": "ximena",
    "name": "Ximena",
    "image": null
  },
  {
    "id": "xolaani",
    "name": "Xolaani",
    "image": null
  },
  {
    "id": "yang",
    "name": "Yang",
    "image": null
  },
  {
    "id": "yrael",
    "name": "Yrael",
    "image": null
  }
]