{
  "id": "isolde",
  "name": "Isolde",
  "origin_region": "shadow-isles",
  "region": "shadow-isles",
  "faction": [
    "shadow-isles"
  ],
  "universe": [],
  "gender": "female",
  "species": [
    "human",
    "wraith"
  ],
  "status": "undead",
  "power_source": "martial-prowess",
  "image": "https://wiki.leagueoflegends.com/en-us/images/Isolde_Render.png?788f6",
  "created_at": "2026-03-31T19:29:17.656892+00:00",
  "description_en": "Isolde was a poor seamstress born in a rural colony within Camavor. In her childhood, she crafted Gwen , a doll that embodied her fantasies of adventure and royalty. One day, the recently appointed king of Camavor, Viego , fell in love at first sight, and asked for her hand in marriage. Viego loved his new wife, so much that he refused to go anywhere without her and focused more on her than ruling his kingdom. This bred contempt from his allies, knowing that Camavor would crumble due to Viego's neglectful rulership. Camavor's enemies took advantage of Viego's ignorance, and sent an assassin to kill Viego using a poisoned blade. The assassination was successfully foiled, but Isolde was accidentally grazed by the dagger and subsequently poisoned. As she slowly succumbed to the poison, Viego's sanity deteriorated as he became more desperate for a cure. His niece and most trusted general Kalista , was sent to find a cure for the Queen's condition. She discovered the Blessed Isles, and learned about the magical Waters of Life in the Isles that could cure the poison. However, Isolde had died before this news had reached Camavor. Viego and his army set forth for the Blessed Isles with Isolde's body. The Isle natives did not let them in and refused to bring Isolde back to life, as they believed that death was not to be subverted. Viego set his army to kill the natives; one survivor, a a custodian of the inner sanctums, instead offered to lead him straight to the Waters of Life. Isolde was lowered into the water, and quickly resurrected into a revenant of pain and anger. In her agony and confusion, she stabbed Viego with his enchanted blade, which caused the blade's magic to amplify into a eruption of Ruination. The Blessed Isles was taken over by a Black Mist and all life on it was destroyed, leaving nothing but the undead souls of the people that remained on the isles. After the Ruination, Isolde's soul was split into many fragments. The fragments spread to many different parts of Runeterra, possessing various people and objects, including Gwen, Senna , and Yorick 's Maiden of the Mist. Years later, Viego was brought back as an immortal being capable of bending the Black Mist to his will. He spread the Black Mist across Runeterra in an effort to assemble all of the pieces of Isolde's soul and bring her back to life. Seeing the harm that he was doing to the world, the Sentinels of Light raced to gather the fragments and defeat the Ruined King. In a final conflict, Viego triumphed over the Sentinels, and successfully assembled Isolde back together. However, Isolde was horrified and saddened by what Viego had become: an obsession that would destroy the world. She wished to be put to rest, prompting Sentinel Akshan to destroy her with his Absolver. The magic of Akshan's weapon revived Gwen and Senna in the process of killing Isolde, and granted her a “true death” where she would rest forever.",
  "related_characters": [
    "Akshan",
    "Gwen",
    "Hecarim",
    "Kalista",
    "Lucian",
    "Maiden of the Mist",
    "Necrit",
    "Senna",
    "Thresh",
    "Viego",
    "Yorick"
  ],
  "description_fr": "Isolde était une pauvre couturière née dans une colonie rurale de Camavor. Dans son enfance, elle a fabriqué Gwen, une poupée qui incarnait ses fantasmes d'aventure et de royauté. Un jour, le nouveau roi de Camavor, Viego, tomba amoureux au premier regard et demanda sa main en mariage. Viego aimait tellement sa nouvelle épouse qu'il refusait d'aller nulle part sans elle et se concentrait davantage sur elle que sur la direction de son royaume. Cela a suscité le mépris de ses alliés, sachant que Camavor s'effondrerait à cause de la gouvernance négligente de Viego. Les ennemis de Camavor ont profité de l'ignorance de Viego et ont envoyé un assassin pour tuer Viego en utilisant une lame empoisonnée. L'assassinat a été déjoué avec succès, mais Isolde a été accidentellement touchée par le poignard puis empoisonnée. Alors qu'elle succombait lentement au poison, la santé mentale de Viego se détériorait à mesure qu'il devenait de plus en plus désespéré à la recherche d'un remède. Sa nièce et général le plus fiable Kalista, fut envoyé pour trouver un remède à l'état de la reine. Elle a découvert les îles bénies et a découvert les eaux magiques de la vie qui pouvaient guérir le poison. Cependant, Isolde était décédée avant que cette nouvelle parvienne à Camavor. Viego et son armée partent pour les Îles Bénies avec le corps d'Isolde. Les indigènes de l'île ne les laissèrent pas entrer et refusèrent de ramener Isolde à la vie, car ils pensaient que la mort ne devait pas être renversée. Viego a envoyé son armée pour tuer les indigènes ; un survivant, gardien des sanctuaires intérieurs, a plutôt proposé de le conduire directement aux eaux de la vie. Isolde fut descendue dans l'eau et ressuscita rapidement pour devenir un revenant de douleur et de colère. Dans son agonie et sa confusion, elle a poignardé Viego avec sa lame enchantée, ce qui a amplifié la magie de la lame en une éruption de Ruine. Les Îles Bénies ont été envahies par une Brume Noire et toute vie y a été détruite, ne laissant que les âmes mortes-vivantes des personnes restées sur les îles. Après la Ruine, l'âme d'Isolde fut divisée en plusieurs fragments. Les fragments se sont répandus dans de nombreuses parties différentes de Runeterra, possédant diverses personnes et objets, notamment Gwen, Senna et la Jeune Fille de la Brume de Yorick. Des années plus tard, Viego fut ramené sous la forme d'un être immortel capable de plier la Brume Noire à sa volonté. Il a répandu la Brume Noire sur Runeterra dans le but d'assembler tous les morceaux de l'âme d'Isolde et de lui redonner vie. Voyant le mal qu'il faisait au monde, les Sentinelles de la Lumière se précipitèrent pour rassembler les fragments et vaincre le Roi Déchu. Dans un conflit final, Viego a triomphé des Sentinelles et a réussi à rassembler Isolde. Cependant, Isolde était horrifiée et attristée par ce qu'était devenu Viego : une obsession qui allait détruire le monde. Elle souhaitait être mise au repos, ce qui a incité la Sentinelle Akshan à la détruire avec son Absolver. La magie de l'arme d'Akshan a ressuscité Gwen et Senna en train de tuer Isolde, et lui a accordé une « vraie mort » où elle reposerait pour toujours."
}