{
  "id": "jarvan_iii",
  "name": "Jarvan III",
  "faction": "demacia",
  "gender": "Male",
  "species": "Human",
  "description": "Ancien Roi de Demacia, père de Jarvan IV. Son règne fut un modèle de vertu, mais il fut assassiné, un événement qui déstabilisa le royaume et précipita la crise des mages.",
  "image": "https://wiki.leagueoflegends.com/en-us/images/04DE010-full.png",
  "created_at": "2025-11-26T17:40:44.99657+00:00",
  "description_en": "Former King of Demacia, and father of Jarvan IV. His reign was a model of virtue, but he was assassinated, an event that destabilized the kingdom and precipitated the mages crisis."
}