{
  "id": "voss",
  "name": "Voss",
  "origin_region": "zaun",
  "region": "zaun",
  "faction": [
    "zaun"
  ],
  "universe": [
    "pre-arcane-runeterra"
  ],
  "gender": "unknown",
  "species": [],
  "status": "unknown",
  "power_source": "chemtech-user",
  "image": "https://wiki.leagueoflegends.com/en-us/images/Default_minor_character_image.png?08d2f",
  "created_at": "2026-03-31T19:41:20.175779+00:00",
  "description_en": "Baron Voss was a chem-baroness who served as the warden of the Dredge, a chemtech prison mine located underneath Zaun. She would sometimes offer freedom in return for a prisoner's tortured confession, which she granted with the edge of her blade. She was eventually forced to abandon the Dredge and flee to Piltover after a violent encounter with Urgot, who took control of the mine in her place.",
  "description_fr": "Le baron Voss était une baronne chimique qui servait de gardien de la Dredge, une mine-prison chimique située sous Zaun. Elle offrait parfois la liberté en échange des aveux torturés d'un prisonnier, qu'elle accordait avec le tranchant de sa lame. Elle fut finalement forcée d'abandonner la Drague et de fuir vers Piltover après une violente rencontre avec Urgot, qui prit le contrôle de la mine à sa place.",
  "related_characters": [
    "Urgot",
    "Warden of Stillwater"
  ]
}