{
  "id": "willump",
  "name": "Willump",
  "origin_region": "freljord",
  "region": "freljord",
  "faction": [
    "freljord"
  ],
  "universe": [],
  "gender": "male",
  "species": [
    "yeti"
  ],
  "status": "alive",
  "power_source": "martial-prowess",
  "image": "https://wiki.leagueoflegends.com/en-us/images/Nunu_Render.png?e499b",
  "created_at": "2026-03-31T19:34:15.596835+00:00",
  "description_en": "Willump was designated the guardian of a crystal which displays the dreams of any nearby mortals. His race was lost when Lissandra nearly freed the Watchers , who descended into savagery after losing their powers—but the guardian remained, determined to protect the last of their power. As the last magical yeti, the guardian had perceptive abilities that let him decide who the magic should be gifted to, and he could find nobody worthy. The humans who found him had only death and bloodshed in mind...and he responded in kind, showing the mortals a monstrous being. As time passed, the guardian began to forget those he loved, even his own name. Once, he knew, there had been song. When a young human boy came to his ruined home, the guardian was ready to kill him like the others. The boy raised his flute like a sword, and the stone came alive with visions of heroes and giants. And yet, the boy never struck. He realized the truth of the songs that led him here: the yeti was not a monster...only lonely. The guardian, prepared to kill, did not expect the first snowball that smashed into his face. Or the second. He became friendlier and furrier, responding not to fear and bloodshed, but to imagination, his growl changing into a laugh. It lasted until he accidentally broke the boy's flute. The boy began to cry. The guardian looked to the crystal and saw a sorrow like his. Where before he had looked into it and saw his people's destruction— the darkness they had buried, betrayal by the blind one —he now saw a caravan burning. A voice on the wind, a song, and something else within the boy awoke. The guardian had not seen this before, not since the three sisters who had first sought him so long ago. He saw love, fighting back despair. This child was the Freljord's only hope, the guardian knew, and it was already within the boy, this power of hope. The magic he had guarded was only a tool, meant to be shaped and guarded by the heart the boy had. The crystal's power entered the boy, infusing him with the ability to make what he imagined come true. To fix his flute with True Ice. To imagine a best friend named Willump. Rambling wildly across the Freljordian plains, Nunu and Willump can now experience something they never could alone: an adventure. The boy's heart and the yeti's strength let them follow the songs of Nunu's mother on their quest to find her. But Willump knows that they have a grave responsibility. For the time when Nunu will need to stand strong is nigh, as the Dark Ice which keeps the Watchers trapped at the heart of the Freljord is melting...",
  "related_characters": [
    "Anivia",
    "Braum",
    "Gnar",
    "Lissandra",
    "Nunu",
    "Ornn",
    "Volibear"
  ],
  "description_fr": "Willump a été désigné comme le gardien d'un cristal qui affiche les rêves de tous les mortels proches. Sa race fut perdue lorsque Lissandra faillit libérer les Veilleurs, qui tombèrent dans la sauvagerie après avoir perdu leurs pouvoirs, mais le gardien resta, déterminé à protéger le reste de leur pouvoir. En tant que dernier yéti magique, le gardien avait des capacités de perception qui lui permettaient de décider à qui la magie devait être offerte, et il ne pouvait trouver personne qui en valait la peine. Les humains qui l'ont trouvé n'avaient en tête que la mort et l'effusion de sang... et il a répondu de la même manière, montrant aux mortels un être monstrueux. Au fil du temps, le gardien commença à oublier ceux qu’il aimait, même son propre nom. Autrefois, il le savait, il y avait eu une chanson. Lorsqu'un jeune garçon humain arriva dans sa maison en ruine, le gardien était prêt à le tuer comme les autres. Le garçon leva sa flûte comme une épée et la pierre prit vie avec des visions de héros et de géants. Et pourtant, le garçon n’a jamais frappé. Il réalisa la vérité des chansons qui l'avaient amené ici : le yéti n'était pas un monstre... seulement solitaire. Le gardien, prêt à tuer, ne s'attendait pas à la première boule de neige qui lui fracassait le visage. Ou le deuxième. Il devint plus amical et plus poilu, ne répondant pas à la peur et à l'effusion de sang, mais à l'imagination, son grognement se transformant en rire. Cela a duré jusqu'à ce qu'il casse accidentellement la flûte du garçon. Le garçon s'est mis à pleurer. Le gardien regarda le cristal et vit un chagrin semblable au sien. Là où auparavant il avait regardé et vu la destruction de son peuple – les ténèbres qu'ils avaient ensevelies, la trahison de l'aveugle – il vit maintenant une caravane en feu. Une voix dans le vent, une chanson et quelque chose d'autre à l'intérieur du garçon se réveilla. Le gardien n'avait pas vu cela auparavant, pas depuis les trois sœurs qui l'avaient cherché il y avait si longtemps. Il a vu l'amour, luttant contre le désespoir. Cet enfant était le seul espoir de Freljord, le tuteur le savait, et il possédait déjà chez le garçon ce pouvoir d'espoir. La magie qu'il avait gardée n'était qu'un outil, destiné à être façonné et gardé par le cœur du garçon. Le pouvoir du cristal est entré dans le garçon, lui conférant la capacité de réaliser ce qu'il imaginait. Pour réparer sa flûte avec True Ice. Imaginer un meilleur ami nommé Willump. En se promenant sauvagement à travers les plaines de Freljord, Nunu et Willump peuvent désormais vivre quelque chose qu'ils n'auraient jamais pu vivre seuls : une aventure. Le cœur du garçon et la force du yéti leur permettent de suivre les chants de la mère de Nunu dans leur quête pour la retrouver. Mais Willump sait qu’ils ont une grave responsabilité. Car le moment où Nunu devra rester fort est proche, alors que la glace noire qui maintient les Veilleurs piégés au cœur de Freljord est en train de fondre..."
}