{
  "id": "zalie",
  "name": "Zalie",
  "origin_region": "piltover",
  "region": "piltover",
  "faction": [
    "piltover"
  ],
  "universe": [
    "runeterra-prime"
  ],
  "gender": "unknown",
  "species": [
    "human"
  ],
  "status": "unknown",
  "power_source": "unknown",
  "image": "https://wiki.leagueoflegends.com/en-us/images/99PZ112-full.png?e286f",
  "created_at": "2026-03-31T19:37:47.300618+00:00",
  "description_en": "A fast-talking, deal-making merchant, Zalie runs the Zalies' Bizarre Bazaar, a shop packed with trinkets, curios, and adventuring gear—everything an explorer might need (except refunds). With an eye for profit and a flair for theatrics, Zalie never lets a sale slip away.",
  "description_fr": "Marchand bavard et négociant, Zalie dirige le Bizarre Bazaar de Zalies, une boutique remplie de bibelots, de bibelots et d'équipement d'aventure, tout ce dont un explorateur pourrait avoir besoin (sauf les remboursements). Avec un sens du profit et un sens du théâtre, Zalie ne laisse jamais échapper une vente.",
  "related_characters": [
    "Ezreal"
  ]
}